silexlight-1.4.0.dist-info/RECORD
silexlight-1.4.0.dist-info/LICENSE
silexlight-1.4.0.dist-info/WHEEL
silexlight-1.4.0.dist-info/METADATA
SILEXlight/silex_lib_tet4_python.py
SILEXlight/silex_lib_tri3_python.py
SILEXlight/silex_lib_tet4_fortran.cpython-312-darwin.so
SILEXlight/__init__.py
SILEXlight/silex_lib_gmsh.py
SILEXlight/silex_lib_tri3_fortran.cpython-312-darwin.so
SILEXlight/tests/test_silex_lib_gmsh.py
SILEXlight/tests/__init__.py
SILEXlight/tests/test_silex_lib_tet4_python.py
SILEXlight/tests/test_silex_lib_tet4_fortran.py
SILEXlight/tests/test_silex_lib_tri3_fortran.py
SILEXlight/tests/test_silex_lib_tri3_python.py
SILEXlight/.dylibs/libgfortran.5.dylib
SILEXlight/.dylibs/libquadmath.0.dylib
SILEXlight/.dylibs/libgcc_s.1.1.dylib
