Metadata-Version: 2.1
Name: SILEXlight
Version: 1.4.0
Summary: Basic SILEX library
Author-Email: Antoine Legay <antoine.legay@lecnam.net>, Luc Laurent <luc.laurent@lecnam.net>
Maintainer-Email: Luc Laurent <luc.laurent@lecnam.net>
License:                    GNU LESSER GENERAL PUBLIC LICENSE
Classifier: License :: OSI Approved :: GNU Lesser General Public License v3 (LGPLv3)
Classifier: Natural Language :: English
Classifier: Operating System :: OS Independent
Classifier: Programming Language :: Python
Classifier: Programming Language :: Python :: 3.9
Classifier: Programming Language :: Python :: 3.10
Classifier: Programming Language :: Python :: 3.11
Classifier: Programming Language :: Python :: 3.12
Classifier: Programming Language :: Python :: 3.13
Classifier: Programming Language :: Fortran
Classifier: Intended Audience :: Education
Classifier: Topic :: Education
Classifier: Topic :: Scientific/Engineering :: Physics
Project-URL: homepage, https://antoinelegay.free.fr
Project-URL: repository, https://github.com/luclaurent/SILEX-light
Requires-Python: >=3.9
Requires-Dist: numpy
Requires-Dist: scipy
Provides-Extra: dev
Requires-Dist: pylint~=2.14.0; extra == "dev"
Requires-Dist: toml~=0.10.2; extra == "dev"
Requires-Dist: yapf~=0.32.0; extra == "dev"
Provides-Extra: test
Requires-Dist: pytest; extra == "test"
Requires-Dist: pytest-cov[all]; extra == "test"
Requires-Dist: pytest-benchmark; extra == "test"
